fast_append_array/__init__.py
fast_append_array/fast_append_array.py
fast_append_array-0.2.0.dist-info/LICENSE
fast_append_array-0.2.0.dist-info/WHEEL
fast_append_array-0.2.0.dist-info/METADATA
fast_append_array-0.2.0.dist-info/RECORD
